Endpoints/__init__.py
Endpoints/championMastery_v4.py
Endpoints/champion_v3.py
Endpoints/leagueExp_v4.py
Endpoints/league_v4.py
Endpoints/lolStatus_v4.py
Endpoints/match_v5.py
Endpoints/spectator_v4.py
Endpoints/summoner_v4.py
RiotWrapper-0.2.3.dist-info/METADATA
RiotWrapper-0.2.3.dist-info/WHEEL
RiotWrapper-0.2.3.dist-info/top_level.txt
RiotWrapper-0.2.3.dist-info/RECORD
